{
    "name": "ewa_analysis_synthesis",
    "description": "Synthesized summary and parameters from an SAP EWA report.",
    "strict": true,
    "schema": {
        "type": "object",
        "properties": {
            "System Health Overview": {
                "type": "object",
                "description": "Overall status of key system areas.",
                "properties": {
                    "Performance": {
                        "type": [
                            "string",
                            "null"
                        ],
                        "enum": [
                            "good",
                            "fair",
                            "poor",
                            null
                        ]
                    },
                    "Security": {
                        "type": [
                            "string",
                            "null"
                        ],
                        "enum": [
                            "good",
                            "fair",
                            "poor",
                            null
                        ]
                    },
                    "Stability": {
                        "type": [
                            "string",
                            "null"
                        ],
                        "enum": [
                            "good",
                            "fair",
                            "poor",
                            null
                        ]
                    },
                    "Configuration": {
                        "type": [
                            "string",
                            "null"
                        ],
                        "enum": [
                            "good",
                            "fair",
                            "poor",
                            null
                        ]
                    }
                },
                "required": [
                    "Performance",
                    "Security",
                    "Stability",
                    "Configuration"
                ],
                "additionalProperties": false
            },
            "Executive Summary": {
                "type": "string",
                "description": "Concise bullet-point summary for a C-level audience."
            },
            "Positive Findings": {
                "type": "array",
                "description": "List of things the system is doing well or configured correctly.",
                "items": {
                    "type": "object",
                    "properties": {
                        "Area": {
                            "type": "string",
                            "description": "The general area, e.g., Security, Performance."
                        },
                        "Description": {
                            "type": "string",
                            "description": "Details of the positive finding."
                        }
                    },
                    "required": [
                        "Area",
                        "Description"
                    ],
                    "additionalProperties": false
                }
            },
            "Capacity Outlook": {
                "type": "object",
                "description": "Metrics related to system growth and utilization.",
                "properties": {
                    "Database Growth": {
                        "type": [
                            "string",
                            "null"
                        ],
                        "description": "E.g., 50GB/month."
                    },
                    "CPU Utilization": {
                        "type": [
                            "string",
                            "null"
                        ],
                        "description": "E.g., Max CPU is 11%."
                    },
                    "Memory Utilization": {
                        "type": [
                            "string",
                            "null"
                        ],
                        "description": "Memory and paging information."
                    },
                    "Summary": {
                        "type": [
                            "string",
                            "null"
                        ],
                        "description": "Overall capacity health statement."
                    }
                },
                "required": [
                    "Database Growth",
                    "CPU Utilization",
                    "Memory Utilization",
                    "Summary"
                ],
                "additionalProperties": false
            },
            "Overall Risk": {
                "type": [
                    "string",
                    "null"
                ],
                "enum": [
                    "low",
                    "medium",
                    "high",
                    null
                ],
                "description": "The aggregated risk level for the entire system based on all findings."
            },
            "Technical Parameters": {
                "type": "object",
                "description": "Key-value pairs of technical SAP/Database parameters extracted from the report.",
                "properties": {
                    "system_role": {
                        "type": [
                            "string",
                            "null"
                        ],
                        "description": "e.g., Production, Test"
                    },
                    "database_type": {
                        "type": [
                            "string",
                            "null"
                        ],
                        "description": "e.g., SAP HANA"
                    },
                    "database_version": {
                        "type": [
                            "string",
                            "null"
                        ],
                        "description": "e.g., 2.00.075.00"
                    },
                    "kernel_release": {
                        "type": [
                            "string",
                            "null"
                        ],
                        "description": "e.g., 793"
                    },
                    "abap_release": {
                        "type": [
                            "string",
                            "null"
                        ],
                        "description": "e.g., SAP S/4HANA 2023"
                    }
                },
                "required": [
                    "system_role",
                    "database_type",
                    "database_version",
                    "kernel_release",
                    "abap_release"
                ],
                "additionalProperties": false
            },
            "Chapters Reviewed": {
                "type": "array",
                "description": "List of all chapters/sections found and reviewed in the EWA document.",
                "items": {
                    "type": "string"
                }
            },
            "Key Findings": {
                "type": "array",
                "items": {
                    "type": "object",
                    "required": [
                        "Issue ID",
                        "Area",
                        "Finding",
                        "Impact",
                        "Business impact",
                        "Severity",
                        "Source"
                    ],
                    "properties": {
                        "Issue ID": {
                            "type": "string",
                            "pattern": "^KF-[0-9]{2}$",
                            "description": "Unique key finding identifier."
                        },
                        "Area": {
                            "type": "string",
                            "description": "Exact Topic text from Check Overview."
                        },
                        "Finding": {
                            "type": "string"
                        },
                        "Impact": {
                            "type": "string",
                            "description": "Potential technical impact."
                        },
                        "Business impact": {
                            "type": "string",
                            "description": "Translated business risk."
                        },
                        "Severity": {
                            "type": "string",
                            "enum": [
                                "medium",
                                "high"
                            ]
                        },
                        "Source": {
                            "type": "string",
                            "description": "Report section or evidence supporting the finding."
                        }
                    }
                }
            },
            "Recommendations": {
                "type": "array",
                "description": "Detailed, actionable recommendations.",
                "items": {
                    "type": "object",
                    "required": [
                        "Recommendation ID",
                        "Estimated Effort",
                        "Responsible Area",
                        "Linked issue ID",
                        "Action",
                        "Preventative Action"
                    ],
                    "properties": {
                        "Recommendation ID": {
                            "type": "string",
                            "pattern": "^REC-[0-9]{2}$"
                        },
                        "Estimated Effort": {
                            "type": "object",
                            "required": [
                                "analysis",
                                "implementation"
                            ],
                            "properties": {
                                "analysis": {
                                    "type": "string",
                                    "enum": [
                                        "low",
                                        "medium",
                                        "high"
                                    ]
                                },
                                "implementation": {
                                    "type": "string",
                                    "enum": [
                                        "low",
                                        "medium",
                                        "high"
                                    ]
                                }
                            }
                        },
                        "Responsible Area": {
                            "type": "string",
                            "enum": [
                                "SAP Basis Team",
                                "Database Administration",
                                "Operating System Administration",
                                "Network & Connectivity",
                                "Security / Compliance Team",
                                "Application Development",
                                "Functional / Business Process Owner",
                                "Infrastructure / Hardware Team",
                                "Third-Party Vendor",
                                "Project / Change Management"
                            ]
                        },
                        "Linked issue ID": {
                            "type": "string",
                            "pattern": "^KF-[0-9]{2}$",
                            "description": "Key finding this recommendation addresses."
                        },
                        "Action": {
                            "type": "string",
                            "description": "Specific steps to execute."
                        },
                        "Preventative Action": {
                            "type": "string",
                            "description": "Measure to prevent recurrence."
                        }
                    }
                }
            }
        },
        "required": [
            "System Health Overview",
            "Executive Summary",
            "Positive Findings",
            "Capacity Outlook",
            "Overall Risk",
            "Technical Parameters",
            "Chapters Reviewed",
            "Key Findings",
            "Recommendations"
        ],
        "additionalProperties": false
    }
}